learning/basic_components/gates/mux.sv
module MUX (
    input a,
    input b,
    input sel,
    output y
);
    assign y = sel ? b : a;
endmodule

learning/basic_components/tb/mux_tb.sv
module mux_tb;
    logic a;
    logic b;
    logic sel;
    logic y;

    MUX dut (
        .a(a),
        .b(b),
        .sel(sel),
        .y(y)
    );

initial begin
        $dumpfile("waves/mux.vcd");
        $dumpvars(0, mux_tb);

        a = 0; b = 0; sel = 0; #10;
        assert(y == 0);
        a = 0; b = 1; sel = 0; #10;
        assert(y == 0);
        a = 1; b = 0; sel = 0; #10;
        assert(y == 1);
        a = 1; b = 1; sel = 0; #10;
        assert(y == 1);

        a = 0; b = 0; sel = 1; #10;
        assert(y == 0);
        a = 0; b = 1; sel = 1; #10;
        assert(y == 1);
        a = 1; b = 0; sel = 1; #10;
        assert(y == 0);
        a = 1; b = 1; sel = 1; #10;
        assert(y == 1);

        $display("MUX gate passed");
        $finish;
    end
endmodule

waves/mux.vcd
$version Generated by VerilatedVcd $end
$timescale 1ps $end
 $scope module $rootio $end
 $upscope $end
 $scope module mux_tb $end
  $var wire 1 # a $end
  $var wire 1 $ b $end
  $var wire 1 % sel $end
  $var wire 1 & y $end
  $scope module dut $end
   $var wire 1 # a $end
   $var wire 1 $ b $end
   $var wire 1 % sel $end
   $var wire 1 & y $end
  $upscope $end
 $upscope $end
$enddefinitions $end


#0
0#
0$
0%
0&
#10
1$
#20
1#
0$
1&
#30
1$
#40
0#
0$
1%
0&
#50
1$
1&
#60
1#
0$
0&
#70
1$
1&
